pybrv/__init__.py
pybrv/create_pybrvmeta.py
pybrv/email_notification.py
pybrv/main.py
pybrv/recommendation.py
pybrv/rule_manager.py
pybrv/utils.py
pybrv/sql_templates/business_rule_check/result.sql
pybrv/sql_templates/business_rule_check/result_postgres.sql
pybrv/sql_templates/common/bookmark_select.sql
pybrv/sql_templates/common/bookmark_select_dbrcks.sql
pybrv/sql_templates/common/bookmark_select_postgres.sql
pybrv/sql_templates/common/bookmark_update.sql
pybrv/sql_templates/common/bookmark_update_dpc_dbrcks.sql
pybrv/sql_templates/common/bookmark_update_dpc_postgres.sql
pybrv/sql_templates/common/bookmark_update_postgres.sql
pybrv/sql_templates/common/clean_up_unit_test_dbrcks.sql
pybrv/sql_templates/common/clean_up_unit_test_pgrs.sql
pybrv/sql_templates/common/unique_identifier_mapping_dbrcks.sql
pybrv/sql_templates/common/unique_identifier_mapping_postgres.sql
pybrv/sql_templates/common/unique_rule_mapping.sql
pybrv/sql_templates/common/unique_rule_mapping_postgres.sql
pybrv/sql_templates/data_parity_check/attribute_summary_report_dbrcks.sql
pybrv/sql_templates/data_parity_check/attribute_summary_report_postgres.sql
pybrv/sql_templates/data_parity_check/dashboard_etl_dbrcks.sql
pybrv/sql_templates/data_parity_check/dashboard_etl_postgres.sql
pybrv/sql_templates/data_parity_check/load_attribute_summary_report_dbrcks.sql
pybrv/sql_templates/data_parity_check/load_attribute_summary_report_postgres.sql
pybrv/sql_templates/data_parity_check/load_summary_report_dbrcks.sql
pybrv/sql_templates/data_parity_check/load_summary_report_postgres.sql
pybrv/sql_templates/data_parity_check/metadata_sql_text.sql
pybrv/sql_templates/data_parity_check/sql_template_dbrcks.sql
pybrv/sql_templates/data_parity_check/sql_template_postgres.sql
pybrv/sql_templates/data_parity_check/summary_report_dbrcks.sql
pybrv/sql_templates/data_parity_check/summary_report_postgres.sql
pybrv/sql_templates/tags/tag.sql
pybrv-0.7.0.dist-info/METADATA
pybrv-0.7.0.dist-info/WHEEL
pybrv-0.7.0.dist-info/entry_points.txt
pybrv-0.7.0.dist-info/top_level.txt
pybrv-0.7.0.dist-info/RECORD
