Metadata-Version: 2.4
Name: pybrv
Version: 0.7.0
Summary: Python Business Rule Validator
Author: Puneet Taneja
Classifier: Development Status :: 3 - Alpha
Classifier: Intended Audience :: Developers
Classifier: Programming Language :: Python :: 3
Classifier: Programming Language :: Python :: 3.7
Requires-Python: >=3.7
Requires-Dist: pandas>=1.3.0
Requires-Dist: sqlalchemy>=1.4.0
Requires-Dist: psycopg2-binary>=2.9.0
Requires-Dist: python-dotenv>=0.19.0
Requires-Dist: databricks-sql-connector>=2.0.0
Requires-Dist: pytz>=2021.1
Requires-Dist: retry>=0.9.2
Requires-Dist: openAI
Dynamic: author
Dynamic: classifier
Dynamic: requires-dist
Dynamic: requires-python
Dynamic: summary
